fastcldf/__init__.py
fastcldf/cli.py
fastcldf-0.1.2.dist-info/LICENSE
fastcldf-0.1.2.dist-info/METADATA
fastcldf-0.1.2.dist-info/WHEEL
fastcldf-0.1.2.dist-info/entry_points.txt
fastcldf-0.1.2.dist-info/RECORD
